[
    {
        "type": "superpixel",
        "nomenclature": "metaphoric",
        "name": ["Lines", "Angulated lines / Polygons / Zig-zag pattern"],
        "aliases": [
            ["Miscellaneous", "Angulated lines / Polygons"]
        ]

    },
    {
        "type": "superpixel",
        "nomenclature": "metaphoric",
        "name": ["Lines", "Atypical pigment network / Reticulation"],
        "aliases": [
            ["Network", "Atypical pigment network / Reticulation"]
        ]

    },
    {
        "type": "superpixel",
        "nomenclature": "metaphoric",
        "name": ["Lines", "Branched streaks"],
        "aliases": []
    },
    {
        "type": "superpixel",
        "nomenclature": "metaphoric",
        "name": ["Lines", "Broadened pigment network / Reticulation"],
        "aliases": [
            ["Network", "Broadened pigment network / Reticulation"]
        ]

    },
    {
        "type": "superpixel",
        "nomenclature": "metaphoric",
        "name": ["Lines", "Cerebriform pattern"],
        "aliases": []
    },
    {
        "type": "superpixel",
        "nomenclature": "metaphoric",
        "name": ["Lines", "Crypts"],
        "aliases": [
            ["Miscellaneous", "Crypts"]
        ]

    },
    {
        "type": "superpixel",
        "nomenclature": "metaphoric",
        "name": ["Lines", "Delicate pigment network / Reticulation"],
        "aliases": [
            ["Network", "Delicate Pigment Network / Reticulation"]
        ]

    },
    {
        "type": "superpixel",
        "nomenclature": "metaphoric",
        "name": ["Lines", "Fibrillar pattern"],
        "aliases": []
    },
    {
        "type": "superpixel",
        "nomenclature": "metaphoric",
        "name": ["Lines", "Fingerprint pattern"],
        "aliases": []
    },
    {
        "type": "superpixel",
        "nomenclature": "metaphoric",
        "name": ["Lines", "Leaf like areas"],
        "aliases": [
            ["Globules / Clods", "Leaflike area"],
            ["Miscellaneous", "Leaflike area"]
        ]

    },
    {
        "type": "superpixel",
        "nomenclature": "metaphoric",
        "name": ["Lines", "Negative pigment network"],
        "aliases": [
            ["Network", "Negative pigment network"]
        ]

    },
    {
        "type": "superpixel",
        "nomenclature": "metaphoric",
        "name": ["Lines", "Parallel furrows pattern (volar lesions)"],
        "aliases": [
            ["Pattern", "Parallel furrow"],
            ["Volar lesions", "Parallel furrow pattern"]
        ]

    },
    {
        "type": "superpixel",
        "nomenclature": "metaphoric",
        "name": ["Lines", "Parallel lines (volar lesions)"],
        "aliases": [
            ["Pattern", "Parallel ridge"],
            ["Volar lesions", "Parallel lines"]
        ]

    },
    {
        "type": "superpixel",
        "nomenclature": "metaphoric",
        "name": ["Lines", "Parallel ridge pattern (volar lesions)"],
        "aliases": [
            ["Volar lesions", "Parallel ridge pattern"]
        ]

    },
    {
        "type": "superpixel",
        "nomenclature": "metaphoric",
        "name": ["Lines", "Pseudopods"],
        "aliases": [
            ["Miscellaneous", "Pseudopods"]
        ]

    },
    {
        "type": "superpixel",
        "nomenclature": "metaphoric",
        "name": ["Lines", "Radial streaming"],
        "aliases": [
            ["Miscellaneous", "Radial streaming"]
        ]

    },
    {
        "type": "superpixel",
        "nomenclature": "metaphoric",
        "name": ["Lines", "Rhomboids (facial skin)"],
        "aliases": []
    },
    {
        "type": "superpixel",
        "nomenclature": "metaphoric",
        "name": ["Lines", "Shiny white streaks"],
        "aliases": []
    },
    {
        "type": "superpixel",
        "nomenclature": "metaphoric",
        "name": ["Lines", "Spoke wheel areas"],
        "aliases": [
            ["Globules / Clods", "Spoke wheel areas"]
        ]

    },
    {
        "type": "superpixel",
        "nomenclature": "metaphoric",
        "name": ["Lines", "Streaks"],
        "aliases": [
            ["Miscellaneous", "Streaks"]
        ]

    },
    {
        "type": "superpixel",
        "nomenclature": "metaphoric",
        "name": ["Lines", "Starburst pattern"],
        "aliases": [
            ["Pattern", "Starburst"]
        ]

    },
    {
        "type": "superpixel",
        "nomenclature": "metaphoric",
        "name": ["Lines", "Typical pigment network / Reticulation"],
        "aliases": [
            ["Network", "Typical pigment network / Reticulation"]
        ]

    },
    {
        "type": "superpixel",
        "nomenclature": "metaphoric",
        "name": ["Lines", "NOS"],
        "aliases": []
    },
    {
        "type": "superpixel",
        "nomenclature": "metaphoric",
        "name": ["Globules / Clods", "Blue"],
        "aliases": []
    },
    {
        "type": "superpixel",
        "nomenclature": "metaphoric",
        "name": ["Globules / Clods", "Blue-gray ovoid nests"],
        "aliases": []
    },
    {
        "type": "superpixel",
        "nomenclature": "metaphoric",
        "name": ["Globules / Clods", "Cobblestone pattern"],
        "aliases": []
    },
    {
        "type": "superpixel",
        "nomenclature": "metaphoric",
        "name": ["Globules / Clods", "Comedo-like openings"],
        "aliases": [
            ["Miscellaneous", "Comedo-like openings"]
        ]

    },
    {
        "type": "superpixel",
        "nomenclature": "metaphoric",
        "name": ["Globules / Clods", "Concentric"],
        "aliases": []
    },
    {
        "type": "superpixel",
        "nomenclature": "metaphoric",
        "name": ["Globules / Clods", "Irregular"],
        "aliases": []
    },
    {
        "type": "superpixel",
        "nomenclature": "metaphoric",
        "name": ["Globules / Clods", "Regular"],
        "aliases": []
    },
    {
        "type": "superpixel",
        "nomenclature": "metaphoric",
        "name": ["Globules / Clods", "Leaflike area"],
        "aliases": [
            ["Lines", "Leaf like areas"],
            ["Miscellaneous", "Leaflike area"]
        ]

    },
    {
        "type": "superpixel",
        "nomenclature": "metaphoric",
        "name": ["Globules / Clods", "Spoke wheel areas"],
        "aliases": [
            ["Lines", "Spoke wheel areas"]
        ]

    },
    {
        "type": "superpixel",
        "nomenclature": "metaphoric",
        "name": ["Globules / Clods", "Milia-like cysts"],
        "aliases": [
            ["Dots", "Milia-like cysts"],
            ["Miscellaneous", "Milia-like cysts, cloudy or starry"]
        ]

    },
    {
        "type": "superpixel",
        "nomenclature": "metaphoric",
        "name": ["Globules / Clods", "Milky red"],
        "aliases": []
    },
    {
        "type": "superpixel",
        "nomenclature": "metaphoric",
        "name": ["Globules / Clods", "Red lacunae"],
        "aliases": []
    },
    {
        "type": "superpixel",
        "nomenclature": "metaphoric",
        "name": ["Globules / Clods", "Rim of brown globules"],
        "aliases": []
    },
    {
        "type": "superpixel",
        "nomenclature": "metaphoric",
        "name": ["Globules / Clods", "Shiny white blotches and strands"],
        "aliases": [
            ["Shiny white structures", "Shiny white blotches and strands"]
        ]

    },
    {
        "type": "superpixel",
        "nomenclature": "metaphoric",
        "name": ["Globules / Clods", "Variant of spoke wheel area"],
        "aliases": []
    },
    {
        "type": "superpixel",
        "nomenclature": "metaphoric",
        "name": ["Globules / Clods", "White"],
        "aliases": []
    },
    {
        "type": "superpixel",
        "nomenclature": "metaphoric",
        "name": ["Globules / Clods", "NOS"],
        "aliases": []
    },
    {
        "type": "superpixel",
        "nomenclature": "metaphoric",
        "name": ["Dots", "Annular-granular pattern"],
        "aliases": [
            ["Facial Skin", "Annular-granular pattern"],
            ["Miscellaneous", "Annular-granular pattern"]
        ]

    },
    {
        "type": "superpixel",
        "nomenclature": "metaphoric",
        "name": ["Dots", "Black"],
        "aliases": []
    },
    {
        "type": "superpixel",
        "nomenclature": "metaphoric",
        "name": ["Dots", "Blue-gray"],
        "aliases": []
    },
    {
        "type": "superpixel",
        "nomenclature": "metaphoric",
        "name": ["Dots", "Brown"],
        "aliases": []
    },
    {
        "type": "superpixel",
        "nomenclature": "metaphoric",
        "name": ["Dots", "Granularity"],
        "aliases": []
    },
    {
        "type": "superpixel",
        "nomenclature": "metaphoric",
        "name": ["Dots", "Irregular"],
        "aliases": []
    },
    {
        "type": "superpixel",
        "nomenclature": "metaphoric",
        "name": ["Dots", "Linear"],
        "aliases": []
    },
    {
        "type": "superpixel",
        "nomenclature": "metaphoric",
        "name": ["Dots", "Milia-like cysts"],
        "aliases": [
            ["Globules / Clods", "Milia-like cysts"],
            ["Miscellaneous", "Milia-like cysts, cloudy or starry"]
        ]

    },
    {
        "type": "superpixel",
        "nomenclature": "metaphoric",
        "name": ["Dots", "Peppering"],
        "aliases": []
    },
    {
        "type": "superpixel",
        "nomenclature": "metaphoric",
        "name": ["Dots", "Regular"],
        "aliases": []
    },
    {
        "type": "superpixel",
        "nomenclature": "metaphoric",
        "name": ["Dots", "Rosettes"],
        "aliases": [
            ["Shiny white structures", "Rosettes"]
        ]

    },
    {
        "type": "superpixel",
        "nomenclature": "metaphoric",
        "name": ["Dots", "Targetoid"],
        "aliases": []
    },
    {
        "type": "superpixel",
        "nomenclature": "metaphoric",
        "name": ["Dots", "Yellow"],
        "aliases": []
    },
    {
        "type": "superpixel",
        "nomenclature": "metaphoric",
        "name": ["Dots", "NOS"],
        "aliases": []
    },
    {
        "type": "superpixel",
        "nomenclature": "metaphoric",
        "name": ["Circles & Semicircles", "Asymmetric follicular openings"],
        "aliases": [
            ["Facial Skin", "Asymmetric follicular openings"]
        ]

    },
    {
        "type": "superpixel",
        "nomenclature": "metaphoric",
        "name": ["Circles & Semicircles", "Brown"],
        "aliases": []
    },
    {
        "type": "superpixel",
        "nomenclature": "metaphoric",
        "name": ["Circles & Semicircles", "Circle within a circle"],
        "aliases": [
            ["Facial Skin", "Circle within a circle"],
            ["Miscellaneous", "Circle within a circle"]
        ]

    },
    {
        "type": "superpixel",
        "nomenclature": "metaphoric",
        "name": ["Circles & Semicircles", "Fish scale (mucosal lesions)"],
        "aliases": []
    },
    {
        "type": "superpixel",
        "nomenclature": "metaphoric",
        "name": ["Circles & Semicircles", "Gray"],
        "aliases": []
    },
    {
        "type": "superpixel",
        "nomenclature": "metaphoric",
        "name": ["Circles & Semicircles", "White"],
        "aliases": []
    },
    {
        "type": "superpixel",
        "nomenclature": "metaphoric",
        "name": ["Circles & Semicircles", "NOS"],
        "aliases": []
    },
    {
        "type": "superpixel",
        "nomenclature": "metaphoric",
        "name": ["Structureless", "Blotch irregular"],
        "aliases": [
            ["Miscellaneous", "Blotch irregular"]
        ]

    },
    {
        "type": "superpixel",
        "nomenclature": "metaphoric",
        "name": ["Structureless", "Blotch regular"],
        "aliases": [
            ["Miscellaneous", "Blotch regular"]
        ]

    },
    {
        "type": "superpixel",
        "nomenclature": "metaphoric",
        "name": ["Structureless", "Blue-whitish veil"],
        "aliases": [
            ["Miscellaneous", "Blue-whitish veil"]
        ]

    },
    {
        "type": "superpixel",
        "nomenclature": "metaphoric",
        "name": ["Structureless", "Central white patch"],
        "aliases": []
    },
    {
        "type": "superpixel",
        "nomenclature": "metaphoric",
        "name": ["Structureless", "Homogeneous pattern", "Blue"],
        "aliases": []
    },
    {
        "type": "superpixel",
        "nomenclature": "metaphoric",
        "name": ["Structureless", "Homogeneous pattern", "Brown"],
        "aliases": []
    },
    {
        "type": "superpixel",
        "nomenclature": "metaphoric",
        "name": ["Structureless", "Homogeneous pattern", "Pink"],
        "aliases": []
    },
    {
        "type": "superpixel",
        "nomenclature": "metaphoric",
        "name": ["Structureless", "Homogeneous pattern", "NOS"],
        "aliases": []
    },
    {
        "type": "superpixel",
        "nomenclature": "metaphoric",
        "name": ["Structureless", "Milky red areas"],
        "aliases": []
    },
    {
        "type": "superpixel",
        "nomenclature": "metaphoric",
        "name": ["Structureless", "Pseudonetwork"],
        "aliases": []
    },
    {
        "type": "superpixel",
        "nomenclature": "metaphoric",
        "name": ["Structureless", "Rainbow pattern"],
        "aliases": []
    },
    {
        "type": "superpixel",
        "nomenclature": "metaphoric",
        "name": ["Structureless", "Scar-like depigmentation"],
        "aliases": []
    },
    {
        "type": "superpixel",
        "nomenclature": "metaphoric",
        "name": ["Structureless", "Strawberry pattern"],
        "aliases": []
    },
    {
        "type": "superpixel",
        "nomenclature": "metaphoric",
        "name": ["Structureless", "Structureless brown (tan)"],
        "aliases": []
    },
    {
        "type": "superpixel",
        "nomenclature": "metaphoric",
        "name": ["Structureless", "NOS"],
        "aliases": []
    },
    {
        "type": "superpixel",
        "nomenclature": "metaphoric",
        "name": ["Vessels", "Arborizing"],
        "aliases": []
    },
    {
        "type": "superpixel",
        "nomenclature": "metaphoric",
        "name": ["Vessels", "Comma"],
        "aliases": []
    },
    {
        "type": "superpixel",
        "nomenclature": "metaphoric",
        "name": ["Vessels", "Corckscrew"],
        "aliases": []
    },
    {
        "type": "superpixel",
        "nomenclature": "metaphoric",
        "name": ["Vessels", "Crown"],
        "aliases": []
    },
    {
        "type": "superpixel",
        "nomenclature": "metaphoric",
        "name": ["Vessels", "Dotted"],
        "aliases": []
    },
    {
        "type": "superpixel",
        "nomenclature": "metaphoric",
        "name": ["Vessels", "Glomerular"],
        "aliases": []
    },
    {
        "type": "superpixel",
        "nomenclature": "metaphoric",
        "name": ["Vessels", "Hairpin"],
        "aliases": []
    },
    {
        "type": "superpixel",
        "nomenclature": "metaphoric",
        "name": ["Vessels", "Linear irregular"],
        "aliases": []
    },
    {
        "type": "superpixel",
        "nomenclature": "metaphoric",
        "name": ["Vessels", "Monomorphous"],
        "aliases": []
    },
    {
        "type": "superpixel",
        "nomenclature": "metaphoric",
        "name": ["Vessels", "Polymorphous"],
        "aliases": []
    },
    {
        "type": "superpixel",
        "nomenclature": "metaphoric",
        "name": ["Vessels", "String of pearls"],
        "aliases": [
            ["Miscellaneous", "String of pearls"]
        ]

    },
    {
        "type": "superpixel",
        "nomenclature": "metaphoric",
        "name": ["Vessels", "Targetoid"],
        "aliases": []
    },
    {
        "type": "superpixel",
        "nomenclature": "metaphoric",
        "name": ["Vessels", "NOS"],
        "aliases": []
    },
    {
        "type": "superpixel",
        "nomenclature": "metaphoric",
        "name": ["Network", "Atypical pigment network / Reticulation"],
        "aliases": [
            ["Lines", "Atypical pigment network / Reticulation"]
        ]

    },
    {
        "type": "superpixel",
        "nomenclature": "metaphoric",
        "name": ["Network", "Broadened pigment network / Reticulation"],
        "aliases": [
            ["Lines", "Broadened pigment network / Reticulation"]
        ]

    },
    {
        "type": "superpixel",
        "nomenclature": "metaphoric",
        "name": ["Network", "Delicate Pigment Network / Reticulation"],
        "aliases": [
            ["Lines", "Delicate pigment network / Reticulation"]
        ]

    },
    {
        "type": "superpixel",
        "nomenclature": "metaphoric",
        "name": ["Network", "Negative pigment network"],
        "aliases": [
            ["Lines", "Negative pigment network"]
        ]

    },
    {
        "type": "superpixel",
        "nomenclature": "metaphoric",
        "name": ["Network", "Typical pigment network / Reticulation"],
        "aliases": [
            ["Lines", "Typical pigment network / Reticulation"]
        ]

    },
    {
        "type": "superpixel",
        "nomenclature": "metaphoric",
        "name": ["Network", "NOS"],
        "aliases": []
    },
    {
        "type": "superpixel",
        "nomenclature": "metaphoric",
        "name": ["Pattern", "Cerebriform"],
        "aliases": []
    },
    {
        "type": "superpixel",
        "nomenclature": "metaphoric",
        "name": ["Pattern", "Fibrilar"],
        "aliases": []
    },
    {
        "type": "superpixel",
        "nomenclature": "metaphoric",
        "name": ["Pattern", "Fingerprint"],
        "aliases": []
    },
    {
        "type": "superpixel",
        "nomenclature": "metaphoric",
        "name": ["Pattern", "Homogeneous", "Blue"],
        "aliases": []
    },
    {
        "type": "superpixel",
        "nomenclature": "metaphoric",
        "name": ["Pattern", "Homogeneous", "Brown"],
        "aliases": []
    },
    {
        "type": "superpixel",
        "nomenclature": "metaphoric",
        "name": ["Pattern", "Homogeneous", "Pink"],
        "aliases": []
    },
    {
        "type": "superpixel",
        "nomenclature": "metaphoric",
        "name": ["Pattern", "Homogeneous", "NOS"],
        "aliases": []
    },
    {
        "type": "superpixel",
        "nomenclature": "metaphoric",
        "name": ["Pattern", "Honeycomb"],
        "aliases": []
    },
    {
        "type": "superpixel",
        "nomenclature": "metaphoric",
        "name": ["Pattern", "Latticelike"],
        "aliases": []
    },
    {
        "type": "superpixel",
        "nomenclature": "metaphoric",
        "name": ["Pattern", "Parallel furrow"],
        "aliases": [
            ["Lines", "Parallel furrows pattern (volar lesions)"],
            ["Volar lesions", "Parallel furrow pattern"]
        ]

    },
    {
        "type": "superpixel",
        "nomenclature": "metaphoric",
        "name": ["Pattern", "Parallel ridge"],
        "aliases": [
            ["Lines", "Parallel lines (volar lesions)"],
            ["Volar lesions", "Parallel lines"]
        ]

    },
    {
        "type": "superpixel",
        "nomenclature": "metaphoric",
        "name": ["Pattern", "Rainbow"],
        "aliases": []
    },
    {
        "type": "superpixel",
        "nomenclature": "metaphoric",
        "name": ["Pattern", "Starburst"],
        "aliases": [
            ["Lines", "Starburst pattern"]
        ]

    },
    {
        "type": "superpixel",
        "nomenclature": "metaphoric",
        "name": ["Pattern", "Strawberry"],
        "aliases": []
    },
    {
        "type": "superpixel",
        "nomenclature": "metaphoric",
        "name": ["Pattern", "NOS"],
        "aliases": []
    },
    {
        "type": "superpixel",
        "nomenclature": "metaphoric",
        "name": ["Regression structures"],
        "aliases": []
    },
    {
        "type": "superpixel",
        "nomenclature": "metaphoric",
        "name": ["Regression structures", "Peppering / Granularity"],
        "aliases": []
    },
    {
        "type": "superpixel",
        "nomenclature": "metaphoric",
        "name": ["Regression structures", "Scarlike depigmentation"],
        "aliases": []
    },
    {
        "type": "superpixel",
        "nomenclature": "metaphoric",
        "name": ["Regression structures", "NOS"],
        "aliases": []
    },
    {
        "type": "superpixel",
        "nomenclature": "metaphoric",
        "name": ["Shiny white structures"],
        "aliases": []
    },
    {
        "type": "superpixel",
        "nomenclature": "metaphoric",
        "name": ["Shiny white structures", "Rosettes"],
        "aliases": [
            ["Dots", "Rosettes"]
        ]

    },
    {
        "type": "superpixel",
        "nomenclature": "metaphoric",
        "name": ["Shiny white structures", "Shiny white blotches and strands"],
        "aliases": [
            ["Globules / Clods", "Shiny white blotches and strands"]
        ]

    },
    {
        "type": "superpixel",
        "nomenclature": "metaphoric",
        "name": ["Shiny white structures", "Shiny white streaks"],
        "aliases": []
    },
    {
        "type": "superpixel",
        "nomenclature": "metaphoric",
        "name": ["Shiny white structures", "NOS"],
        "aliases": []
    },
    {
        "type": "superpixel",
        "nomenclature": "metaphoric",
        "name": ["Facial Skin", "Annular-granular pattern"],
        "aliases": [
            ["Dots", "Annular-granular pattern"],
            ["Miscellaneous", "Annular-granular pattern"]
        ]

    },
    {
        "type": "superpixel",
        "nomenclature": "metaphoric",
        "name": ["Facial Skin", "Asymmetric follicular openings"],
        "aliases": [
            ["Circles & Semicircles", "Asymmetric follicular openings"]
        ]

    },
    {
        "type": "superpixel",
        "nomenclature": "metaphoric",
        "name": ["Facial Skin", "Brown circles"],
        "aliases": []
    },
    {
        "type": "superpixel",
        "nomenclature": "metaphoric",
        "name": ["Facial Skin", "Circle within a circle"],
        "aliases": [
            ["Circles & Semicircles", "Circle within a circle"],
            ["Miscellaneous", "Circle within a circle"]
        ]

    },
    {
        "type": "superpixel",
        "nomenclature": "metaphoric",
        "name": ["Facial Skin", "Pseudonetwork"],
        "aliases": [
            ["Miscellaneous", "Pseudonetwork"]
        ]

    },
    {
        "type": "superpixel",
        "nomenclature": "metaphoric",
        "name": ["Facial Skin", "Rhomboids / Zig-zag pattern"],
        "aliases": []
    },
    {
        "type": "superpixel",
        "nomenclature": "metaphoric",
        "name": ["Volar lesions", "Parallel furrow pattern"],
        "aliases": [
            ["Lines", "Parallel furrows pattern (volar lesions)"],
            ["Pattern", "Parallel furrow"]
        ]

    },
    {
        "type": "superpixel",
        "nomenclature": "metaphoric",
        "name": ["Volar lesions", "Fibrilar pattern"],
        "aliases": []
    },
    {
        "type": "superpixel",
        "nomenclature": "metaphoric",
        "name": ["Volar lesions", "Latticelike pattern"],
        "aliases": []
    },
    {
        "type": "superpixel",
        "nomenclature": "metaphoric",
        "name": ["Volar lesions", "Parallel lines"],
        "aliases": [
            ["Lines", "Parallel lines (volar lesions)"],
            ["Pattern", "Parallel ridge"]
        ]

    },
    {
        "type": "superpixel",
        "nomenclature": "metaphoric",
        "name": ["Volar lesions", "Parallel ridge pattern"],
        "aliases": [
            ["Lines", "Parallel ridge pattern (volar lesions)"]
        ]

    },
    {
        "type": "superpixel",
        "nomenclature": "metaphoric",
        "name": ["Nail lesions", "Blood spots"],
        "aliases": [
            ["Miscellaneous", "Blood spots"]
        ]

    },
    {
        "type": "superpixel",
        "nomenclature": "metaphoric",
        "name": ["Nail lesions", "Granular inclusions"],
        "aliases": []
    },
    {
        "type": "superpixel",
        "nomenclature": "metaphoric",
        "name": ["Nail lesions", "Hutchinson sign"],
        "aliases": [
            ["Miscellaneous", "Hutchinson sign"]
        ]

    },
    {
        "type": "superpixel",
        "nomenclature": "metaphoric",
        "name": ["Nail lesions", "Irregular lines"],
        "aliases": []
    },
    {
        "type": "superpixel",
        "nomenclature": "metaphoric",
        "name": ["Nail lesions", "Pseudo-Hutchinson sign"],
        "aliases": [
            ["Miscellaneous", "Pseudo-Hutchinson sign"]
        ]

    },
    {
        "type": "superpixel",
        "nomenclature": "metaphoric",
        "name": ["Nail lesions", "Splinter hemorrhage"],
        "aliases": []
    },
    {
        "type": "superpixel",
        "nomenclature": "metaphoric",
        "name": ["Nail lesions", "Regular lines"],
        "aliases": []
    },
    {
        "type": "superpixel",
        "nomenclature": "metaphoric",
        "name": ["Miscellaneous", "Angulated lines / Polygons"],
        "aliases": [
            ["Lines", "Angulated lines / Polygons / Zig-zag pattern"]
        ]

    },
    {
        "type": "superpixel",
        "nomenclature": "metaphoric",
        "name": ["Miscellaneous", "Annular-granular pattern"],
        "aliases": [
            ["Dots", "Annular-granular pattern"],
            ["Facial Skin", "Annular-granular pattern"]
        ]

    },
    {
        "type": "superpixel",
        "nomenclature": "metaphoric",
        "name": ["Miscellaneous", "Asymmetric pigmented follicular openings"],
        "aliases": []
    },
    {
        "type": "superpixel",
        "nomenclature": "metaphoric",
        "name": ["Miscellaneous", "Black lacunae"],
        "aliases": []
    },
    {
        "type": "superpixel",
        "nomenclature": "metaphoric",
        "name": ["Miscellaneous", "Blood spots"],
        "aliases": [
            ["Nail lesions", "Blood spots"]
        ]

    },
    {
        "type": "superpixel",
        "nomenclature": "metaphoric",
        "name": ["Miscellaneous", "Blotch irregular"],
        "aliases": [
            ["Structureless", "Blotch irregular"]
        ]

    },
    {
        "type": "superpixel",
        "nomenclature": "metaphoric",
        "name": ["Miscellaneous", "Blotch regular"],
        "aliases": [
            ["Structureless", "Blotch regular"]
        ]

    },
    {
        "type": "superpixel",
        "nomenclature": "metaphoric",
        "name": ["Miscellaneous", "Blue lacunae"],
        "aliases": []
    },
    {
        "type": "superpixel",
        "nomenclature": "metaphoric",
        "name": ["Miscellaneous", "Blue-whitish veil"],
        "aliases": [
            ["Structureless", "Blue-whitish veil"]
        ]

    },
    {
        "type": "superpixel",
        "nomenclature": "metaphoric",
        "name": ["Miscellaneous", "Circle within a circle"],
        "aliases": [
            ["Circles & Semicircles", "Circle within a circle"],
            ["Facial Skin", "Circle within a circle"]
        ]

    },
    {
        "type": "superpixel",
        "nomenclature": "metaphoric",
        "name": ["Miscellaneous", "Comedo-like openings"],
        "aliases": [
            ["Globules / Clods", "Comedo-like openings"]
        ]

    },
    {
        "type": "superpixel",
        "nomenclature": "metaphoric",
        "name": ["Miscellaneous", "Crypts"],
        "aliases": [
            ["Lines", "Crypts"]
        ]

    },
    {
        "type": "superpixel",
        "nomenclature": "metaphoric",
        "name": ["Miscellaneous", "Disruption of parallelism"],
        "aliases": []
    },
    {
        "type": "superpixel",
        "nomenclature": "metaphoric",
        "name": ["Miscellaneous", "Fissures"],
        "aliases": []
    },
    {
        "type": "superpixel",
        "nomenclature": "metaphoric",
        "name": ["Miscellaneous", "Granularity or granules"],
        "aliases": []
    },
    {
        "type": "superpixel",
        "nomenclature": "metaphoric",
        "name": ["Miscellaneous", "Hutchinson sign"],
        "aliases": [
            ["Nail lesions", "Hutchinson sign"]
        ]

    },
    {
        "type": "superpixel",
        "nomenclature": "metaphoric",
        "name": ["Miscellaneous", "Leaflike area"],
        "aliases": [
            ["Lines", "Leaf like areas"],
            ["Globules / Clods", "Leaflike area"]
        ]

    },
    {
        "type": "superpixel",
        "nomenclature": "metaphoric",
        "name": ["Miscellaneous", "Milia-like cysts, cloudy or starry"],
        "aliases": [
            ["Globules / Clods", "Milia-like cysts"],
            ["Dots", "Milia-like cysts"]
        ]

    },
    {
        "type": "superpixel",
        "nomenclature": "metaphoric",
        "name": ["Miscellaneous", "Moth-eaten border"],
        "aliases": []
    },
    {
        "type": "superpixel",
        "nomenclature": "metaphoric",
        "name": ["Miscellaneous", "Pseudo-Hutchinson sign"],
        "aliases": [
            ["Nail lesions", "Pseudo-Hutchinson sign"]
        ]

    },
    {
        "type": "superpixel",
        "nomenclature": "metaphoric",
        "name": ["Miscellaneous", "Pseudonetwork"],
        "aliases": [
            ["Facial Skin", "Pseudonetwork"]
        ]

    },
    {
        "type": "superpixel",
        "nomenclature": "metaphoric",
        "name": ["Miscellaneous", "Pseudopods"],
        "aliases": [
            ["Lines", "Pseudopods"]
        ]

    },
    {
        "type": "superpixel",
        "nomenclature": "metaphoric",
        "name": ["Miscellaneous", "Radial streaming"],
        "aliases": [
            ["Lines", "Radial streaming"]
        ]

    },
    {
        "type": "superpixel",
        "nomenclature": "metaphoric",
        "name": ["Miscellaneous", "Red lacunae"],
        "aliases": []
    },
    {
        "type": "superpixel",
        "nomenclature": "metaphoric",
        "name": ["Miscellaneous", "Red-purple lacunae"],
        "aliases": []
    },
    {
        "type": "superpixel",
        "nomenclature": "metaphoric",
        "name": ["Miscellaneous", "Regularly bended ribbon sign"],
        "aliases": []
    },
    {
        "type": "superpixel",
        "nomenclature": "metaphoric",
        "name": ["Miscellaneous", "Rhomboids / Zig-zag pattern"],
        "aliases": []
    },
    {
        "type": "superpixel",
        "nomenclature": "metaphoric",
        "name": ["Miscellaneous", "Ridges"],
        "aliases": []
    },
    {
        "type": "superpixel",
        "nomenclature": "metaphoric",
        "name": ["Miscellaneous", "Scale"],
        "aliases": []
    },
    {
        "type": "superpixel",
        "nomenclature": "metaphoric",
        "name": ["Miscellaneous", "Setting-sun pattern"],
        "aliases": []
    },
    {
        "type": "superpixel",
        "nomenclature": "metaphoric",
        "name": ["Miscellaneous", "Spoke wheel area"],
        "aliases": []
    },
    {
        "type": "superpixel",
        "nomenclature": "metaphoric",
        "name": ["Miscellaneous", "Streaks"],
        "aliases": [
            ["Lines", "Streaks"]
        ]

    },
    {
        "type": "superpixel",
        "nomenclature": "metaphoric",
        "name": ["Miscellaneous", "String of pearls"],
        "aliases": [
            ["Vessels", "String of pearls"]
        ]

    },
    {
        "type": "superpixel",
        "nomenclature": "metaphoric",
        "name": ["Miscellaneous", "Structureless, brown (tan)"],
        "aliases": []
    },
    {
        "type": "superpixel",
        "nomenclature": "metaphoric",
        "name": ["Miscellaneous", "Twisted red loops"],
        "aliases": []
    },
    {
        "type": "superpixel",
        "nomenclature": "metaphoric",
        "name": ["Miscellaneous", "Ulceration / Erosion"],
        "aliases": []
    }
]
